CHANGELOG.txt
LICENSE.txt
MANIFEST.in
README.txt
setup.py
amitcalculator/__init__.py
amitcalculator/stat.py
amitcalculator.egg-info/PKG-INFO
amitcalculator.egg-info/SOURCES.txt
amitcalculator.egg-info/dependency_links.txt
amitcalculator.egg-info/top_level.txt