Metadata-Version: 2.1
Name: amitcalculator
Version: 0.0.2
Summary: Basic arithmetic calculator
Home-page: UNKNOWN
Author: Amit Bendale
Author-email: amitb2108@gmail.com
License: UNKNOWN
Keywords: calculator
Platform: UNKNOWN
Classifier: Development Status :: 5 - Production/Stable
Classifier: Intended Audience :: Education
Classifier: Operating System :: MacOS
Classifier: License :: OSI Approved :: MIT License
Classifier: Programming Language :: Python :: 3
License-File: LICENSE.txt
